mdx_superscript.py
MarkdownSuperscript-2.1.1.dist-info/AUTHORS.rst
MarkdownSuperscript-2.1.1.dist-info/LICENSE
MarkdownSuperscript-2.1.1.dist-info/METADATA
MarkdownSuperscript-2.1.1.dist-info/WHEEL
MarkdownSuperscript-2.1.1.dist-info/entry_points.txt
MarkdownSuperscript-2.1.1.dist-info/top_level.txt
MarkdownSuperscript-2.1.1.dist-info/RECORD
