Metadata-Version: 1.1
Name: MarkdownSuperscript
Version: 2.1.1
Summary: Python-Markdown extension to allow for superscript text.
Home-page: https://github.com/jambonrose/markdown_superscript_extension
Author: Andrew Pinkham
Author-email: UNKNOWN
License: Simplified BSD License
Project-URL: Documentation, https://markdown-superscript-extension.rtfd.io/en/stable/
Project-URL: Source, https://github.com/jambonrose/markdown_superscript_extension
Project-URL: Tracker, https://github.com/jambonrose/markdown_superscript_extension/issues
Keywords: text,filter,markdown,html,superscript
Platform: UNKNOWN
Classifier: Development Status :: 5 - Production/Stable
Classifier: Environment :: Console
Classifier: Intended Audience :: Developers
Classifier: License :: OSI Approved :: BSD License
Classifier: Operating System :: OS Independent
Classifier: Programming Language :: Python :: 2
Classifier: Programming Language :: Python :: 2.7
Classifier: Programming Language :: Python :: 3
Classifier: Programming Language :: Python :: 3.3
Classifier: Programming Language :: Python :: 3.4
Classifier: Programming Language :: Python :: 3.5
Classifier: Programming Language :: Python :: 3.6
Classifier: Programming Language :: Python :: 3.7
Classifier: Programming Language :: Python :: Implementation :: CPython
Classifier: Programming Language :: Python :: Implementation :: PyPy
Classifier: Topic :: Software Development :: Libraries :: Python Modules
Classifier: Topic :: Text Processing :: Filters
Classifier: Topic :: Text Processing :: Markup :: HTML
